air_telemetry/__init__.py
air_telemetry/endpoint.py
air_telemetry-0.1.1.dist-info/LICENSE
air_telemetry-0.1.1.dist-info/METADATA
air_telemetry-0.1.1.dist-info/WHEEL
air_telemetry-0.1.1.dist-info/top_level.txt
air_telemetry-0.1.1.dist-info/RECORD
