Metadata-Version: 2.1
Name: air-telemetry
Version: 0.1.1
Summary: Online logger compatible with Telemetry servers
Home-page: https://github.com/berrysauce/telemetry
Author: berrysauce
Author-email: contact@berrysauce.me
License: UNKNOWN
Project-URL: Bug Tracker, https://github.com/berrysauce/telemetry/issues
Platform: UNKNOWN
Classifier: Programming Language :: Python :: 3
Classifier: License :: OSI Approved :: GNU General Public License v3 (GPLv3)
Classifier: Operating System :: OS Independent
Requires-Python: >=3.6
License-File: LICENSE
